AIH_SDK/AIHClient.py
AIH_SDK/AIHExceptions.py
AIH_SDK/Object.py
AIH_SDK/__init__.py
AIH_SDK/v1Object.py
AIH_SDK/v2Object.py
AIH_SDK/Assets/AssetsObject.py
AIH_SDK/Assets/Category.py
AIH_SDK/Assets/Classification.py
AIH_SDK/Assets/Equipment.py
AIH_SDK/Assets/MainSystem.py
AIH_SDK/Assets/Organization.py
AIH_SDK/Assets/Plant.py
AIH_SDK/Assets/PropertyDefinition.py
AIH_SDK/Assets/__init__.py
AIH_SDK/DataProcessing/DataProcessingObject.py
AIH_SDK/DataProcessing/Job.py
AIH_SDK/DataProcessing/JobConfiguration.py
AIH_SDK/DataProcessing/JobDefinition.py
AIH_SDK/DataProcessing/__init__.py
AIH_SDK/Designations/Category.py
AIH_SDK/Designations/Classification.py
AIH_SDK/Designations/Design.py
AIH_SDK/Designations/DesignationsObject.py
AIH_SDK/Designations/PropertyDefinition.py
AIH_SDK/Designations/Schema.py
AIH_SDK/Designations/Structure.py
AIH_SDK/Designations/__init__.py
AIH_SDK/Files/DataType.py
AIH_SDK/Files/File.py
AIH_SDK/Files/FilesObject.py
AIH_SDK/Files/__init__.py
AIH_SDK/Identity/IdentityObject.py
AIH_SDK/Identity/Role.py
AIH_SDK/Identity/Team.py
AIH_SDK/Identity/User.py
AIH_SDK/Identity/__init__.py
AIH_SDK/Maintenance/Activity.py
AIH_SDK/Maintenance/ActivityTemplate.py
AIH_SDK/Maintenance/ActivityType.py
AIH_SDK/Maintenance/Category.py
AIH_SDK/Maintenance/Classification.py
AIH_SDK/Maintenance/Deviation.py
AIH_SDK/Maintenance/MaintenanceObject.py
AIH_SDK/Maintenance/Media.py
AIH_SDK/Maintenance/MediaReference.py
AIH_SDK/Maintenance/PropertyDefinition.py
AIH_SDK/Maintenance/WorkItem.py
AIH_SDK/Maintenance/WorkTemplate.py
AIH_SDK/Maintenance/__init__.py
AIH_SDK/Monitors/Category.py
AIH_SDK/Monitors/Classification.py
AIH_SDK/Monitors/Model.py
AIH_SDK/Monitors/ModelDefinition.py
AIH_SDK/Monitors/Monitor.py
AIH_SDK/Monitors/MonitorsObject.py
AIH_SDK/Monitors/PropertyDefinition.py
AIH_SDK/Monitors/__init__.py
AIH_SDK/Risks/Category.py
AIH_SDK/Risks/Classification.py
AIH_SDK/Risks/Mitigation.py
AIH_SDK/Risks/Population.py
AIH_SDK/Risks/PopulationItem.py
ZEVIT_AIH_SDK-0.5.13.dist-info/LICENSE
ZEVIT_AIH_SDK-0.5.13.dist-info/METADATA
ZEVIT_AIH_SDK-0.5.13.dist-info/WHEEL
ZEVIT_AIH_SDK-0.5.13.dist-info/top_level.txt
ZEVIT_AIH_SDK-0.5.13.dist-info/RECORD
