Metadata-Version: 2.1
Name: ZEVIT-AIH-SDK
Version: 0.5.13
Summary: Python SDK to connect with ZEVIT Asset Integrity Hub
Home-page: UNKNOWN
Author: Mikkel Schmidt
Author-email: sebastian.hansen@zevit.net
License: UNKNOWN
Platform: UNKNOWN
Classifier: Programming Language :: Python :: 3
Classifier: License :: OSI Approved :: MIT License
Classifier: Operating System :: OS Independent
Requires-Python: >=3.8
Requires-Dist: numpyencoder
Requires-Dist: pandas
Requires-Dist: numpy
Requires-Dist: requests
Requires-Dist: requests-oauthlib
Requires-Dist: oauthlib
Requires-Dist: pickleshare
Requires-Dist: Pillow
